askbot
askbot_site
testproject
