Metadata-Version: 2.4
Name: askbot
Version: 0.12.3
Summary: Question and Answer forum, like StackOverflow, written in python and Django
Home-page: http://askbot.org
Author: Evgeny.Fadeev
Author-email: evgeny.fadeev@gmail.com
License: GPLv3
Keywords: forum,community,wiki,Q&A
Classifier: Development Status :: 4 - Beta
Classifier: Environment :: Web Environment
Classifier: Framework :: Django
Classifier: Intended Audience :: Developers
Classifier: License :: OSI Approved :: GNU General Public License (GPL)
Classifier: Natural Language :: English
Classifier: Natural Language :: Finnish
Classifier: Natural Language :: German
Classifier: Natural Language :: Russian
Classifier: Natural Language :: Serbian
Classifier: Natural Language :: Turkish
Classifier: Operating System :: OS Independent
Classifier: Programming Language :: Python :: 3
Classifier: Programming Language :: JavaScript
Classifier: Topic :: Communications :: Usenet News
Classifier: Topic :: Communications :: Email :: Mailing List Servers
Classifier: Topic :: Communications
Classifier: Topic :: Internet :: WWW/HTTP :: WSGI :: Application
Requires-Python: >=3.8
License-File: LICENSE
License-File: COPYING
License-File: AUTHORS
Requires-Dist: aiohttp<4.0
Requires-Dist: django-appconf==1.0.5
Requires-Dist: akismet==1.0.1
Requires-Dist: django-avatar>=7.0
Requires-Dist: bleach==5.0.1
Requires-Dist: beautifulsoup4<=4.7.1
Requires-Dist: django-compressor<=4.4,>=3.0
Requires-Dist: celery==5.3.0
Requires-Dist: django<5.0,>=3.0
Requires-Dist: django-countries>=3.3
Requires-Dist: django-jinja>=2.0
Requires-Dist: django-followit==0.6.0
Requires-Dist: html5lib==1.1
Requires-Dist: Jinja2<3.1,>=2.10
Requires-Dist: jinja2-simple-tags==0.5.0
Requires-Dist: jsonfield>=2.0.0
Requires-Dist: pyjwt<=1.7.1
Requires-Dist: django-keyedcache3>=1.5.1
Requires-Dist: django-livesettings3==1.6.3
Requires-Dist: markdown2<=2.3.9
Requires-Dist: markupsafe
Requires-Dist: mock==3.0.5
Requires-Dist: oauth2<=1.9.0.post1
Requires-Dist: python-openid2>=3.0
Requires-Dist: django-picklefield<=3.0.1,>=1.0.0
Requires-Dist: django-recaptcha==3.0.0
Requires-Dist: python-cas<1.7,>=1.4.0
Requires-Dist: premailer==3.10.0
Requires-Dist: psycopg2-binary>=2.9.6
Requires-Dist: okta-jwt-verifier==0.2.3
Requires-Dist: responses<=0.23.1,>=0.9.0
Requires-Dist: requests-oauthlib>=1.2.0
Requires-Dist: requirements-parser>=0.2.0
Requires-Dist: django-robots==5.0
Requires-Dist: regex
Requires-Dist: unidecode
Requires-Dist: urllib3<1.27,>=1.21.1
Dynamic: author
Dynamic: author-email
Dynamic: classifier
Dynamic: description
Dynamic: description-content-type
Dynamic: home-page
Dynamic: keywords
Dynamic: license
Dynamic: license-file
Dynamic: requires-dist
Dynamic: summary
